{
  "name": "Line",
  "videos": [
    {
      "description": "تجربة عنوان",
      "sources": "https://raw.githubusercontent.com/reemdevapp/apps/main/raw/v1.mp4",
      "subtitle": "By Google",
      "thumb": "https://rootsooft.github.io/apps/imgplay1.webp",
      "title": "For Bigger Blazes"
    },
    {
      "description": "تجربة عنوان",
      "sources": "https://raw.githubusercontent.com/reemdevapp/apps/main/raw/v2.mp4",
      "subtitle": "By Google",
      "thumb": "https://rootsooft.github.io/apps/imgplay2.webp",
      "title": "For Bigger Escape"
    },
    {
      "description": "تجربة عنوان",
      "sources": "https://raw.githubusercontent.com/reemdevapp/apps/main/raw/v3.mp4",
      "subtitle": "By Google",
      "thumb": "https://rootsooft.github.io/apps/imgplay3.webp",
      "title": "For Bigger Fun"
    },
    {
     "description": "تجربة عنوان",
      "sources": "https://raw.githubusercontent.com/reemdevapp/apps/main/raw/v4.mp4",
      "subtitle": "By Google",
      "thumb": "https://rootsooft.github.io/apps/imgplay4.webp",
      "title": "For Bigger Joyrides"
    },
    {
      "description": "تجربة عنوان",
      "sources": "https://raw.githubusercontent.com/reemdevapp/apps/main/raw/v5.mp4",
      "subtitle": "By Google",
      "thumb": "https://rootsooft.github.io/apps/imgplay5.webp",
      "title": "For Bigger Meltdowns"
    },
    {
     "description": "تجربة عنوان",
      "sources": "https://raw.githubusercontent.com/reemdevapp/apps/main/raw/v6.mp4",
      "subtitle": "By Garage419",
      "thumb": "https://rootsooft.github.io/apps/imgplay6.webp",
      "title": "We Are Going On Bullrun"
    },
    {
      "description": "تجربة عنوان",
      "sources": "https://raw.githubusercontent.com/reemdevapp/apps/main/raw/v7.mp4",
      "subtitle": "By Google",
      "thumb": "https://rootsooft.github.io/apps/imgplay7.webp",
      "title": "For Bigger Blazes"
    },
    {
      "description": "تجربة عنوان",
      "sources": "https://raw.githubusercontent.com/reemdevapp/apps/main/raw/v8.mp4",
      "subtitle": "By Google",
      "thumb": "https://rootsooft.github.io/apps/imgplay8.webp",
      "title": "For Bigger Joyrides"
    }
  ]
}
