{
  "update": [
    {
      "status": "23",
      "app_new_version": "23",
      "app_redirect_url": "https://play.google.com/store/apps/details?id=absdev.com.vpwld",
      "app_update_desc": "حمله الآن من منصة جوجل بلاي",
      "app_update_status": "false",
      "cancel_update_status": "true",
      "redirect_url": "https://play.google.com/store/apps/details?id=absdev.com.vpwld"
    }
  ],
  "settings": [
    {
      "fcm_notification_topic": "absdev_vpwld_topic",
      "onesignal_app_id": "f9ef7826-e744-4321-bafa-2067f41b7a02",
      "privacy_policy_url": "https://absdevpv.blogspot.com/p/privacy-policy.html"
    }
  ],
  "notification": [
    {
      "fcm_notification_topic": "absdev_vpwld_topic",
      "onesignal_app_id": "f9ef7826-e744-4321-bafa-2067f41b7a02"
    }
  ],
  "ads": [
    {
      "ad_status": "on",
      "ad_gdpr_status": "on",
      "big_ad_status": "on",
      "inter_status": "on",
      "admob_app_open": "on",
      "ad_network": "admob",
      "admob_small_banner": "ca-app-pub-3940256099942544/6300978111",
      "admob_medium_banner": "ca-app-pub-3940256099942544/6300978111",
      "admob_inter": "ca-app-pub-3940256099942544/8691691433",
      "admob_native": "ca-app-pub-3940256099942544/2247696110",
      "admob_publisher_id": "ca-app-pub-1778309717892354~8550062729",
      "admob_app_open_unit_id": "ca-app-pub-3940256099942544/3419835294",
      "facebook_small_banner": "ca-app-pub-1778309717892354~8550062729",
      "facebook_medium_banner": "VID_HD_16_9_15S_APP_INSTALL#YOUR_PLACEMENT_ID",
      "facebook_inter": "VID_HD_16_9_15S_APP_INSTALL#YOUR_PLACEMENT_ID",
      "facebook_native": "VID_HD_16_9_15S_APP_INSTALL#YOUR_PLACEMENT_ID",
      "applovin_small_banner": "c5fa87d1dfd51b4d",
      "applovin_medium_banner": "c5fa87d1dfd51b4d",
      "applovin_inter": "781dbc69cc014a5e",
      "applovin_native": "80d0709565e1129c",
      "startapp_app_id": "204425496",
      "unity_game_id": "4613148",
      "banner_unity_id": "0",
      "interstitial_unity_id": "0",
      "inter_clicks": 3
    }
  ]
}

